elite/__init__.py
elite/cipher.py
elite/scheme.py
elite/secret.py
elite/test.py
elite/utils.py
Elite-1.1.1.dist-info/LICENSE.txt
Elite-1.1.1.dist-info/METADATA
Elite-1.1.1.dist-info/WHEEL
Elite-1.1.1.dist-info/top_level.txt
Elite-1.1.1.dist-info/RECORD
