Metadata-Version: 2.1
Name: Elite
Version: 1.1.1
Summary: A lightweight module for elliptic-curve security schemes.
Home-page: https://github.com/origamizyt/Elite
Author: origamizyt
Author-email: zhaoyitong18@163.com
License: UNKNOWN
Platform: UNKNOWN
Classifier: Programming Language :: Python :: 3
Classifier: License :: OSI Approved :: MIT License
Classifier: Operating System :: OS Independent
Requires-Python: >=3
Requires-Dist: ecdsa
Requires-Dist: PyCryptodome
